mcp_gsuite/__init__.py
mcp_gsuite/calendar.py
mcp_gsuite/gauth.py
mcp_gsuite/gmail.py
mcp_gsuite/server.py
mcp_gsuite/toolhandler.py
mcp_gsuite/tools_calendar.py
mcp_gsuite/tools_gmail.py
mcp_gsuite_enhancement-0.4.1rc5.dist-info/METADATA
mcp_gsuite_enhancement-0.4.1rc5.dist-info/WHEEL
mcp_gsuite_enhancement-0.4.1rc5.dist-info/entry_points.txt
mcp_gsuite_enhancement-0.4.1rc5.dist-info/licenses/LICENSE
mcp_gsuite_enhancement-0.4.1rc5.dist-info/RECORD
