Metadata-Version: 2.4
Name: mcp-gsuite-enhancement
Version: 0.4.1rc5
Summary: MCP Server to connect to Google G-Suite
Project-URL: Homepage, https://github.com/isdaniel/mcp-gsuite/tree/enhance-auth-flow
Project-URL: Repository, https://github.com/isdaniel/mcp-gsuite/tree/enhance-auth-flow
Author-email: Daniel Shih <dog830228@gmail.com>
License-File: LICENSE
Requires-Python: >=3.13
Requires-Dist: beautifulsoup4>=4.12.3
Requires-Dist: google-api-python-client>=2.154.0
Requires-Dist: httplib2>=0.22.0
Requires-Dist: mcp>=1.3.0
Requires-Dist: oauth2client==4.1.3
Requires-Dist: python-dotenv>=1.0.1
Requires-Dist: pytz>=2024.2
Requires-Dist: requests>=2.32.3
